omlet/__init__.py
omlet/distributed/__init__.py
omlet/distributed/mpi.py
omlet/distributed/torch_dist.py
omlet/learn/__init__.py
omlet/learn/layers.py
omlet/learn/transformer/__init__.py
omlet/learn/transformer/encoder.py
omlet/lightning/__init__.py
omlet/lightning/callbacks.py
omlet/lightning/checkpoint.py
omlet/lightning/core.py
omlet/lightning/loggers.py
omlet/lightning/records.py
omlet/lightning/trainer.py
omlet/utils/__init__.py
omlet/utils/config_utils.py
omlet/utils/file_utils.py
omlet/utils/json_yaml_utils.py
omlet/utils/logging_utils.py
omlet/utils/metrics.py
omlet/utils/misc_utils.py
omlet/utils/print_utils.py
omlet/utils/termcolor.py
omlet/utils/timer.py
omlet/utils/torch_utils.py
omlet/utils/tracer.py
omlet/utils/video_utils.py
omlet-0.1.dist-info/LICENSE
omlet-0.1.dist-info/METADATA
omlet-0.1.dist-info/WHEEL
omlet-0.1.dist-info/entry_points.txt
omlet-0.1.dist-info/top_level.txt
omlet-0.1.dist-info/RECORD
