Metadata-Version: 2.1
Name: omlet
Version: 0.1
Summary: research project
Home-page: UNKNOWN
Author: Lab
License: MIT
Keywords: Deep Learning,Machine Learning
Platform: UNKNOWN
Classifier: Development Status :: 3 - Alpha
Classifier: Topic :: Scientific/Engineering :: Artificial Intelligence
Classifier: Environment :: Console
Classifier: Programming Language :: Python :: 3
Classifier: License :: OSI Approved :: MIT License
Requires-Python: >=3.7
